WordleGuesser/__init__.py
WordleGuesser/wordle/__init__.py
WordleGuesser/wordle/guesser.py
WordleGuesser/wordle/utils.py
WordleGuesser/wordle/words.py
WordleGuesser-0.1.0.dist-info/LICENSE.txt
WordleGuesser-0.1.0.dist-info/METADATA
WordleGuesser-0.1.0.dist-info/WHEEL
WordleGuesser-0.1.0.dist-info/top_level.txt
WordleGuesser-0.1.0.dist-info/RECORD
