Metadata-Version: 2.1
Name: WordleGuesser
Version: 0.1.0
Summary: A package to determine the best Wordle guesses.
Author: Patrick McCullough
License: UNKNOWN
Platform: UNKNOWN
Classifier: Programming Language :: Python :: 3
Classifier: License :: OSI Approved :: MIT License
Classifier: Operating System :: OS Independent
Requires-Python: >=3
License-File: LICENSE.txt
